{
    "made_by": "@siam3310",
    "last_update_time": "2026-03-16 20:32:56 UTC",
    "scraped_media": [
        {
            "name": "Gopal Bhar",
            "year": null,
            "quality": null,
            "link": "https://atryh78.b-cdn.net/s3/upload/videos/2026/03/[Fibwatch.Com]Gopal.Bhar.S13E1235-1236.mkv"
        },
        {
            "name": "Now You See Me Now You Dont  Dual",
            "year": "2025",
            "quality": "1080p",
            "link": "https://atryh78.b-cdn.net/s3/upload/videos/2026/03/[Fibwatch.Com]Now.You.See.Me.Now.You.Dont.(2025).Dual.1080p.mkv"
        },
        {
            "name": "Indian Idol",
            "year": "2025",
            "quality": "1080p",
            "link": "https://atryh78.b-cdn.net/s3/upload/videos/2026/03/[Fibwatch.Com]Indian.Idol.(2025).S16E45.1080p.mkv"
        },
        {
            "name": "User Not Found",
            "year": null,
            "quality": null,
            "link": "https://atryh78.b-cdn.net/s3/upload/videos/2026/03/[Fibwatch.Com]User.Not.Found.S01E03.Bengali.mkv"
        },
        {
            "name": "Chandrabindoo 2025 Bengali HDTV",
            "year": null,
            "quality": "1080p",
            "link": "https://atryh78.b-cdn.net/s3/upload/videos/2026/03/[Fibwatch.Com]Chandrabindoo.2025.Bengali.HDTV.1080p.mkv"
        },
        {
            "name": "Sultan Abdul Hamid",
            "year": null,
            "quality": "1080p",
            "link": "https://atryh78.b-cdn.net/s3/upload/videos/2026/03/[Fibwatch.Com]Sultan.Abdul.Hamid.S01E108.Bengali.ORG.1080p.mkv"
        },
        {
            "name": "Chandrabindoo 2025 Bengali HDTV",
            "year": null,
            "quality": "480p",
            "link": "https://atryh78.b-cdn.net/s3/upload/videos/2026/03/[Fibwatch.Com]Chandrabindoo.2025.Bengali.HDTV.480p.mkv"
        },
        {
            "name": "Sa Re Ga Ma Pa 2025",
            "year": null,
            "quality": "720p",
            "link": "https://atryh78.b-cdn.net/s3/upload/videos/2026/03/[Fibwatch.Com]Sa.Re.Ga.Ma.Pa.2025.S22E56.720p.mkv"
        },
        {
            "name": "The 50",
            "year": null,
            "quality": "1080P",
            "link": "https://atryh78.b-cdn.net/s3/upload/videos/2026/03/[Fibwatch.Com]The.50.S01E43.1080P.mkv"
        },
        {
            "name": "Nut Boltu",
            "year": null,
            "quality": null,
            "link": "https://atryh78.b-cdn.net/s3/upload/videos/2026/03/[Fibwatch.Com]Nut.Boltu.S11E1029-1030.mkv"
        },
        {
            "name": "Indian Idol",
            "year": "2025",
            "quality": "720p",
            "link": "https://atryh78.b-cdn.net/s3/upload/videos/2026/03/[Fibwatch.Com]Indian.Idol.(2025).S16E45.720p.mkv"
        },
        {
            "name": "Chandrabindoo 2025 Bengali HDTV",
            "year": null,
            "quality": "720p",
            "link": "https://atryh78.b-cdn.net/s3/upload/videos/2026/03/[Fibwatch.Com]Chandrabindoo.2025.Bengali.HDTV.720p.mkv"
        },
        {
            "name": "Now You See Me Now You Dont  Dual",
            "year": "2025",
            "quality": "480p",
            "link": "https://atryh78.b-cdn.net/s3/upload/videos/2026/03/[Fibwatch.Com]Now.You.See.Me.Now.You.Dont.(2025).Dual.480p.mkv"
        },
        {
            "name": "The 50",
            "year": null,
            "quality": "720P",
            "link": "https://atryh78.b-cdn.net/s3/upload/videos/2026/03/[Fibwatch.Com]The.50.S01E43.720P.mkv"
        },
        {
            "name": "Sa Re Ga Ma Pa 2025",
            "year": null,
            "quality": "1080p",
            "link": "https://atryh78.b-cdn.net/s3/upload/videos/2026/03/[Fibwatch.Com]Sa.Re.Ga.Ma.Pa.2025.S22E56.1080p.mkv"
        },
        {
            "name": "Now You See Me Now You Dont  Dual",
            "year": "2025",
            "quality": "720p",
            "link": "https://atryh78.b-cdn.net/s3/upload/videos/2026/03/[Fibwatch.Com]Now.You.See.Me.Now.You.Dont.(2025).Dual.720p.mkv"
        },
        {
            "name": "Laughter Chefs Unlimited Entertainment",
            "year": null,
            "quality": "1080P",
            "link": "https://atryh78.b-cdn.net/s3/upload/videos/2026/03/[Fibwatch.Com]Laughter.Chefs.Unlimited.Entertainment.S03E34.Hindi.1080P..mkv"
        },
        {
            "name": "Naagin",
            "year": null,
            "quality": "720P",
            "link": "https://atryh78.b-cdn.net/s3/upload/videos/2026/03/[Fibwatch.Com]Naagin.S07E24.720P.mkv"
        },
        {
            "name": "Laughter Chefs Unlimited Entertainment",
            "year": null,
            "quality": "720P",
            "link": "https://atryh78.b-cdn.net/s3/upload/videos/2026/03/[Fibwatch.Com]Laughter.Chefs.Unlimited.Entertainment.S03E34.Hindi.720P.mkv"
        },
        {
            "name": "Sultan Abdul Hamid",
            "year": null,
            "quality": "720p",
            "link": "https://atryh78.b-cdn.net/s3/upload/videos/2026/03/[Fibwatch.Com]Sultan.Abdul.Hamid.S01E108.Bengali.ORG.720p.mkv"
        },
        {
            "name": "Restless 2011  Dual",
            "year": null,
            "quality": "720p",
            "link": "https://atryh78.b-cdn.net/s3/upload/videos/2026/03/[Fibwatch.Com]Restless.2011.720p.Dual.mkv"
        },
        {
            "name": "MTV Splitsvilla X6",
            "year": "2026",
            "quality": "720P",
            "link": "https://atryh78.b-cdn.net/s3/upload/videos/2026/03/[Fibwatch.Com]MTV.Splitsvilla.X6.(2026).S16E30.Hindi.720P.mkv"
        },
        {
            "name": "The Hermit  Hindi Dubbed HQ",
            "year": "2025",
            "quality": "720p",
            "link": "https://atryh78.b-cdn.net/s3/upload/videos/2026/03/[Fibwatch.Com]The.Hermit.(2025).Hindi.Dubbed.HQ.720p.mkv"
        },
        {
            "name": "Sardar 2022 Dual",
            "year": null,
            "quality": "720p",
            "link": "https://atryh78.b-cdn.net/s3/upload/videos/2026/03/[Fibwatch.Com]Sardar.2022.Dual.720p.mkv"
        },
        {
            "name": "Sultan Abdul Hamid",
            "year": null,
            "quality": "1080p",
            "link": "https://atryh78.b-cdn.net/s3/upload/videos/2026/03/[Fibwatch.Com]Sultan.Abdul.Hamid.S01E107.Bengali.ORG.1080p.mkv"
        },
        {
            "name": "The 50",
            "year": null,
            "quality": "720P",
            "link": "https://atryh78.b-cdn.net/s3/upload/videos/2026/03/[Fibwatch.Com]The.50.S01E42.720P.mkv"
        },
        {
            "name": "MTV Splitsvilla X6",
            "year": "2026",
            "quality": "1080P",
            "link": "https://atryh78.b-cdn.net/s3/upload/videos/2026/03/[Fibwatch.Com]MTV.Splitsvilla.X6.(2026).S16E30.Hindi.1080P.mkv"
        },
        {
            "name": "Sultan Abdul Hamid",
            "year": null,
            "quality": "720p",
            "link": "https://atryh78.b-cdn.net/s3/upload/videos/2026/03/[Fibwatch.Com]Sultan.Abdul.Hamid.S01E107.Bengali.ORG.720p.mkv"
        },
        {
            "name": "Fast N Loud",
            "year": null,
            "quality": null,
            "link": "https://atryh78.b-cdn.net/s3/upload/videos/2026/03/[Fibwatch.Com]Fast.N.Loud.S01E16-20.Dual.mkv"
        },
        {
            "name": "Restless 2011  Dual",
            "year": null,
            "quality": "1080p",
            "link": "https://atryh78.b-cdn.net/s3/upload/videos/2026/03/[Fibwatch.Com]Restless.2011.1080p.Dual.mkv"
        },
        {
            "name": "User Not Found",
            "year": null,
            "quality": null,
            "link": "https://atryh78.b-cdn.net/s3/upload/videos/2026/03/[Fibwatch.Com]User.Not.Found.S01E02.Bengali.mkv"
        },
        {
            "name": "Laughter Chefs Unlimited Entertainment",
            "year": null,
            "quality": "1080P",
            "link": "https://atryh78.b-cdn.net/s3/upload/videos/2026/03/[Fibwatch.Com]Laughter.Chefs.Unlimited.Entertainment.S03E33.Hindi.1080P.mkv"
        },
        {
            "name": "CID Bangla",
            "year": null,
            "quality": "1080p",
            "link": "https://atryh78.b-cdn.net/s3/upload/videos/2026/03/[Fibwatch.Com]CID.Bangla.S02E86.1080p.mkv"
        },
        {
            "name": "Naagin",
            "year": null,
            "quality": "1080P",
            "link": "https://atryh78.b-cdn.net/s3/upload/videos/2026/03/[Fibwatch.Com]Naagin.S07E24.1080P.mkv"
        },
        {
            "name": "The Hermit  Hindi Dubbed HQ",
            "year": "2025",
            "quality": "1080p",
            "link": "https://atryh78.b-cdn.net/s3/upload/videos/2026/03/[Fibwatch.Com]The.Hermit.(2025).Hindi.Dubbed.HQ.1080p.mkv"
        },
        {
            "name": "Sardar 2022 Dual",
            "year": null,
            "quality": "480p",
            "link": "https://atryh78.b-cdn.net/s3/upload/videos/2026/03/[Fibwatch.Com]Sardar.2022.Dual.480p.mkv"
        },
        {
            "name": "CID Bangla",
            "year": null,
            "quality": "480p",
            "link": "https://atryh78.b-cdn.net/s3/upload/videos/2026/03/[Fibwatch.Com]CID.Bangla.S02E86.480p.mkv"
        },
        {
            "name": "Laughter Chefs Unlimited Entertainment",
            "year": null,
            "quality": "720P",
            "link": "https://atryh78.b-cdn.net/s3/upload/videos/2026/03/[Fibwatch.Com]Laughter.Chefs.Unlimited.Entertainment.S03E33.Hindi.720P.mkv"
        },
        {
            "name": "Sardar 2022 Dual",
            "year": null,
            "quality": "1080p",
            "link": "https://atryh78.b-cdn.net/s3/upload/videos/2026/03/[Fibwatch.Com]Sardar.2022.Dual.1080p.mkv"
        },
        {
            "name": "CID Bangla",
            "year": null,
            "quality": "720p",
            "link": "https://atryh78.b-cdn.net/s3/upload/videos/2026/03/[Fibwatch.Com]CID.Bangla.S02E86.720p.mkv"
        },
        {
            "name": "Sa Re Ga Ma Pa 2025",
            "year": null,
            "quality": "1080p",
            "link": "https://atryh78.b-cdn.net/s3/upload/videos/2026/03/[Fibwatch.Com]Sa.Re.Ga.Ma.Pa.2025.S22E55.1080p.mkv"
        },
        {
            "name": "MTV Splitsvilla X6",
            "year": "2026",
            "quality": "720P",
            "link": "https://atryh78.b-cdn.net/s3/upload/videos/2026/03/[Fibwatch.Com]MTV.Splitsvilla.X6.(2026).S16E29.Hindi.720P.mkv"
        },
        {
            "name": "Indian Idol",
            "year": "2025",
            "quality": "720p",
            "link": "https://atryh78.b-cdn.net/s3/upload/videos/2026/03/[Fibwatch.Com]Indian.Idol.(2025).S16E44.720p.mkv"
        },
        {
            "name": "Ramyaa  Hindi HDTC",
            "year": "2026",
            "quality": "1080p",
            "link": "https://atryh78.b-cdn.net/s3/upload/videos/2026/03/[Fibwatch.Com]Ramyaa.(2026).Hindi.HDTC.1080p.mkv"
        },
        {
            "name": "CID Bangla",
            "year": null,
            "quality": "480p",
            "link": "https://atryh78.b-cdn.net/s3/upload/videos/2026/03/[Fibwatch.Com]CID.Bangla.S02E85.480p.mkv"
        },
        {
            "name": "Sa Re Ga Ma Pa 2025",
            "year": null,
            "quality": "720p",
            "link": "https://atryh78.b-cdn.net/s3/upload/videos/2026/03/[Fibwatch.Com]Sa.Re.Ga.Ma.Pa.2025.S22E55.720p.mkv"
        },
        {
            "name": "The Great Indian Kapil Show",
            "year": null,
            "quality": "1080P",
            "link": "https://atryh78.b-cdn.net/s3/upload/videos/2026/03/[Fibwatch.Com]The.Great.Indian.Kapil.Show.S04E13.1080P.mkv"
        },
        {
            "name": "Monarch Legacy of Monsters",
            "year": null,
            "quality": "720p",
            "link": "https://atryh78.b-cdn.net/s3/upload/videos/2026/03/[Fibwatch.Com]Monarch.Legacy.of.Monsters.S02E03.English.720p.mkv"
        },
        {
            "name": "Legends of the Condor Heroes The Gallants  Dual",
            "year": "2025",
            "quality": "480p",
            "link": "https://atryh78.b-cdn.net/s3/upload/videos/2026/03/[Fibwatch.Com]Legends.of.the.Condor.Heroes.The.Gallants.(2025).Dual.480p.mkv"
        },
        {
            "name": "Naagin",
            "year": null,
            "quality": "1080P",
            "link": "https://atryh78.b-cdn.net/s3/upload/videos/2026/03/[Fibwatch.Com]Naagin.S07E23.1080P.mkv"
        },
        {
            "name": "Naagin",
            "year": null,
            "quality": "720P",
            "link": "https://atryh78.b-cdn.net/s3/upload/videos/2026/03/[Fibwatch.Com]Naagin.S07E23.720P.mkv"
        },
        {
            "name": "Legends of the Condor Heroes The Gallants  Dual",
            "year": "2025",
            "quality": "720p",
            "link": "https://atryh78.b-cdn.net/s3/upload/videos/2026/03/[Fibwatch.Com]Legends.of.the.Condor.Heroes.The.Gallants.(2025).Dual.720p.mkv"
        },
        {
            "name": "Legends of the Condor Heroes The Gallants  Dual",
            "year": "2025",
            "quality": "1080p",
            "link": "https://atryh78.b-cdn.net/s3/upload/videos/2026/03/[Fibwatch.Com]Legends.of.the.Condor.Heroes.The.Gallants.(2025).Dual.1080p.mkv"
        },
        {
            "name": "Ramyaa  Hindi HDTC",
            "year": "2026",
            "quality": "720p",
            "link": "https://atryh78.b-cdn.net/s3/upload/videos/2026/03/[Fibwatch.Com]Ramyaa.(2026).Hindi.HDTC.720p.mkv"
        },
        {
            "name": "Ramyaa  Hindi HDTC",
            "year": "2026",
            "quality": "480p",
            "link": "https://atryh78.b-cdn.net/s3/upload/videos/2026/03/[Fibwatch.Com]Ramyaa.(2026).Hindi.HDTC.480p.mkv"
        },
        {
            "name": "Indian Idol",
            "year": "2025",
            "quality": "1080p",
            "link": "https://atryh78.b-cdn.net/s3/upload/videos/2026/03/[Fibwatch.Com]Indian.Idol.(2025).S16E44.1080p.mkv"
        },
        {
            "name": "The Great Indian Kapil Show",
            "year": null,
            "quality": "720P",
            "link": "https://atryh78.b-cdn.net/s3/upload/videos/2026/03/[Fibwatch.Com]The.Great.Indian.Kapil.Show.S04E13.720P.mkv"
        },
        {
            "name": "Monarch Legacy of Monsters",
            "year": null,
            "quality": "1080p",
            "link": "https://atryh78.b-cdn.net/s3/upload/videos/2026/03/[Fibwatch.Com]Monarch.Legacy.of.Monsters.S02E03.English.1080p.mkv"
        },
        {
            "name": "MTV Splitsvilla X6",
            "year": "2026",
            "quality": "1080P",
            "link": "https://atryh78.b-cdn.net/s3/upload/videos/2026/03/[Fibwatch.Com]MTV.Splitsvilla.X6.(2026).S16E29.Hindi.1080P.mkv"
        },
        {
            "name": "The 50",
            "year": null,
            "quality": "1080P",
            "link": "https://atryh78.b-cdn.net/s3/upload/videos/2026/03/[Fibwatch.Com]The.50.S01E42.1080P.mkv"
        },
        {
            "name": "Wheel Of Fortune",
            "year": "2026",
            "quality": "1080P",
            "link": "https://atryh78.b-cdn.net/s3/upload/videos/2026/03/[Fibwatch.Com]Wheel.Of.Fortune.(2026).S01E34.Hindi.1080P.mkv"
        },
        {
            "name": "CID Bangla",
            "year": null,
            "quality": "720p",
            "link": "https://atryh78.b-cdn.net/s3/upload/videos/2026/03/[Fibwatch.Com]CID.Bangla.S02E85.720p.mkv"
        },
        {
            "name": "Andha Pyaar 2 0",
            "year": null,
            "quality": "1080P",
            "link": "https://atryh78.b-cdn.net/s3/upload/videos/2026/03/[Fibwatch.Com]Andha.Pyaar.2.0.S01E01.1080P.mkv"
        },
        {
            "name": "Wheel Of Fortune",
            "year": "2026",
            "quality": "1080P",
            "link": "https://atryh78.b-cdn.net/s3/upload/videos/2026/03/[Fibwatch.Com]Wheel.Of.Fortune.(2026).S01E32-33.Hindi.1080P.mkv"
        },
        {
            "name": "The Critic 2023  Dual BluRay",
            "year": null,
            "quality": "720p",
            "link": "https://atryh78.b-cdn.net/s3/upload/videos/2026/03/[Fibwatch.Com]The.Critic.2023.720p.Dual.BluRay.mkv"
        },
        {
            "name": "Kissa Court Kachahari Ka  Hindi HDTC",
            "year": "2026",
            "quality": "480p",
            "link": "https://atryh78.b-cdn.net/s3/upload/videos/2026/03/[Fibwatch.Com]Kissa.Court.Kachahari.Ka.(2026).Hindi.HDTC.480p.mkv"
        },
        {
            "name": "The 50",
            "year": null,
            "quality": "1080P",
            "link": "https://atryh78.b-cdn.net/s3/upload/videos/2026/03/[Fibwatch.Com]The.50.S01E41.1080P.mkv"
        },
        {
            "name": "The Critic 2023  Dual BluRay",
            "year": null,
            "quality": "1080p",
            "link": "https://atryh78.b-cdn.net/s3/upload/videos/2026/03/[Fibwatch.Com]The.Critic.2023.1080p.Dual.BluRay.mkv"
        },
        {
            "name": "User Not Found",
            "year": null,
            "quality": null,
            "link": "https://atryh78.b-cdn.net/s3/upload/videos/2026/03/[Fibwatch.Com]User.Not.Found.S01E01.Bengali.mkv"
        },
        {
            "name": "Kissa Court Kachahari Ka  Hindi HDTC",
            "year": "2026",
            "quality": "720p",
            "link": "https://atryh78.b-cdn.net/s3/upload/videos/2026/03/[Fibwatch.Com]Kissa.Court.Kachahari.Ka.(2026).Hindi.HDTC.720p.mkv"
        },
        {
            "name": "Parasakthi  Hindi Dubbed",
            "year": "2026",
            "quality": "1080p",
            "link": "https://atryh78.b-cdn.net/s3/upload/videos/2026/03/[Fibwatch.Com]Parasakthi.(2026).Hindi.Dubbed.1080p.mkv"
        },
        {
            "name": "Parasakthi  Hindi Dubbed",
            "year": "2026",
            "quality": "720p",
            "link": "https://atryh78.b-cdn.net/s3/upload/videos/2026/03/[Fibwatch.Com]Parasakthi.(2026).Hindi.Dubbed.720p.mkv"
        },
        {
            "name": "Wheel Of Fortune",
            "year": "2026",
            "quality": "720P",
            "link": "https://atryh78.b-cdn.net/s3/upload/videos/2026/03/[Fibwatch.Com]Wheel.Of.Fortune.(2026).S01E34.Hindi.720P.mkv"
        },
        {
            "name": "The 50",
            "year": null,
            "quality": "720P",
            "link": "https://atryh78.b-cdn.net/s3/upload/videos/2026/03/[Fibwatch.Com]The.50.S01E41.720P.mkv"
        },
        {
            "name": "Wheel Of Fortune",
            "year": "2026",
            "quality": "720P",
            "link": "https://atryh78.b-cdn.net/s3/upload/videos/2026/03/[Fibwatch.Com]Wheel.Of.Fortune.(2026).S01E32-33.Hindi.720P.mkv"
        },
        {
            "name": "Andha Pyaar 2 0",
            "year": null,
            "quality": "720P",
            "link": "https://atryh78.b-cdn.net/s3/upload/videos/2026/03/[Fibwatch.Com]Andha.Pyaar.2.0.S01E01.720P.mkv"
        },
        {
            "name": "CID Bangla",
            "year": null,
            "quality": "1080p",
            "link": "https://atryh78.b-cdn.net/s3/upload/videos/2026/03/[Fibwatch.Com]CID.Bangla.S02E85.1080p.mkv"
        },
        {
            "name": "The Critic 2023  Dual BluRay",
            "year": null,
            "quality": "480p",
            "link": "https://atryh78.b-cdn.net/s3/upload/videos/2026/03/[Fibwatch.Com]The.Critic.2023.480p.Dual.BluRay.mkv"
        },
        {
            "name": "Parasakthi  Hindi Dubbed",
            "year": "2026",
            "quality": "480p",
            "link": "https://atryh78.b-cdn.net/s3/upload/videos/2026/03/[Fibwatch.Com]Parasakthi.(2026).Hindi.Dubbed.480p.mkv"
        },
        {
            "name": "Kissa Court Kachahari Ka  Hindi HDTC",
            "year": "2026",
            "quality": "1080p",
            "link": "https://atryh78.b-cdn.net/s3/upload/videos/2026/03/[Fibwatch.Com]Kissa.Court.Kachahari.Ka.(2026).Hindi.HDTC.1080p.mkv"
        },
        {
            "name": "Good Fortune  Dual",
            "year": "2025",
            "quality": "1080P",
            "link": "https://atryh78.b-cdn.net/s3/upload/videos/2026/03/[Fibwatch.Com]Good.Fortune.(2025).Dual.1080P.mkv"
        },
        {
            "name": "Good Fortune  Dual",
            "year": "2025",
            "quality": "720P",
            "link": "https://atryh78.b-cdn.net/s3/upload/videos/2026/03/[Fibwatch.Com]Good.Fortune.(2025).Dual.720P.mkv"
        },
        {
            "name": "The 50",
            "year": null,
            "quality": "1080P",
            "link": "https://atryh78.b-cdn.net/s3/upload/videos/2026/03/[Fibwatch.Com]The.50.S01E40.1080P.mkv"
        },
        {
            "name": "Fatal Seduction",
            "year": null,
            "quality": "1080P",
            "link": "https://atryh78.b-cdn.net/s3/upload/videos/2026/03/[Fibwatch.Com]Fatal.Seduction.S03.Dual.1080P.mkv"
        },
        {
            "name": "That Night",
            "year": "2026",
            "quality": "720P",
            "link": "https://atryh78.b-cdn.net/s3/upload/videos/2026/03/[Fibwatch.Com]That.Night.(2026).S01.Dual.720P.mkv"
        },
        {
            "name": "Fatal Seduction",
            "year": null,
            "quality": "720P",
            "link": "https://atryh78.b-cdn.net/s3/upload/videos/2026/03/[Fibwatch.Com]Fatal.Seduction.S03.Dual.720P.mkv"
        },
        {
            "name": "Baba yaga spaseat mir  Russia",
            "year": "2023",
            "quality": "1080P",
            "link": "https://atryh78.b-cdn.net/s3/upload/videos/2026/03/[Fibwatch.Com]Baba.yaga.spaseat.mir.(2023).Russia.1080P.mkv"
        },
        {
            "name": "Dynasty The Murdochs",
            "year": null,
            "quality": "480p",
            "link": "https://atryh78.b-cdn.net/s3/upload/videos/2026/03/[Fibwatch.Com]Dynasty.The.Murdochs.S01.Dual.480p.mkv"
        },
        {
            "name": "That Night",
            "year": "2026",
            "quality": "1080P",
            "link": "https://atryh78.b-cdn.net/s3/upload/videos/2026/03/[Fibwatch.Com]That.Night.(2026).S01.Dual.1080P.mkv"
        },
        {
            "name": "Dynasty The Murdochs",
            "year": null,
            "quality": "720p",
            "link": "https://atryh78.b-cdn.net/s3/upload/videos/2026/03/[Fibwatch.Com]Dynasty.The.Murdochs.S01.Dual.720p.mkv"
        },
        {
            "name": "MTV Splitsvilla X6",
            "year": "2026",
            "quality": "720P",
            "link": "https://atryh78.b-cdn.net/s3/upload/videos/2026/03/[Fibwatch.Com]MTV.Splitsvilla.X6.(2026).S16E28.Hindi.720P.mkv"
        },
        {
            "name": "The Pitt",
            "year": null,
            "quality": "1080p",
            "link": "https://atryh78.b-cdn.net/s3/upload/videos/2026/03/[Fibwatch.Com]The.Pitt.S02E10.Dual.1080p.mkv"
        },
        {
            "name": "The 50",
            "year": null,
            "quality": "720P",
            "link": "https://atryh78.b-cdn.net/s3/upload/videos/2026/03/[Fibwatch.Com]The.50.S01E40.720P.mkv"
        },
        {
            "name": "That Night",
            "year": "2026",
            "quality": "480P",
            "link": "https://atryh78.b-cdn.net/s3/upload/videos/2026/03/[Fibwatch.Com]That.Night.(2026).S01.Dual.480P.mkv"
        },
        {
            "name": "MTV Splitsvilla X6",
            "year": "2026",
            "quality": "1080P",
            "link": "https://atryh78.b-cdn.net/s3/upload/videos/2026/03/[Fibwatch.Com]MTV.Splitsvilla.X6.(2026).S16E28.Hindi.1080P.mkv"
        },
        {
            "name": "Dynasty The Murdochs",
            "year": null,
            "quality": "1080p",
            "link": "https://atryh78.b-cdn.net/s3/upload/videos/2026/03/[Fibwatch.Com]Dynasty.The.Murdochs.S01.Dual.1080p.mkv"
        },
        {
            "name": "Good Fortune  Dual",
            "year": "2025",
            "quality": "480P",
            "link": "https://atryh78.b-cdn.net/s3/upload/videos/2026/03/[Fibwatch.Com]Good.Fortune.(2025).Dual.480P.mkv"
        },
        {
            "name": "Baba yaga spaseat mir  Russia",
            "year": "2023",
            "quality": "720P",
            "link": "https://atryh78.b-cdn.net/s3/upload/videos/2026/03/[Fibwatch.Com]Baba.yaga.spaseat.mir.(2023).Russia.720P.mkv"
        },
        {
            "name": "Fatal Seduction",
            "year": null,
            "quality": "480P",
            "link": "https://atryh78.b-cdn.net/s3/upload/videos/2026/03/[Fibwatch.Com]Fatal.Seduction.S03.Dual.480P.mkv"
        },
        {
            "name": "The Pitt",
            "year": null,
            "quality": "720p",
            "link": "https://atryh78.b-cdn.net/s3/upload/videos/2026/03/[Fibwatch.Com]The.Pitt.S02E10.Dual.720p.mkv"
        },
        {
            "name": "The 50",
            "year": null,
            "quality": "720P",
            "link": "https://atryh78.b-cdn.net/s3/upload/videos/2026/03/[Fibwatch.Com]The.50.S01E39.720P.mkv"
        },
        {
            "name": "Wheel Of Fortune",
            "year": "2026",
            "quality": "1080P",
            "link": "https://atryh78.b-cdn.net/s3/upload/videos/2026/03/[Fibwatch.Com]Wheel.Of.Fortune.(2026).S01E30-31.Hindi.1080P.mkv"
        },
        {
            "name": "Virgin River",
            "year": null,
            "quality": "480p",
            "link": "https://atryh78.b-cdn.net/s3/upload/videos/2026/03/[Fibwatch.Com]Virgin.River.S01.480p.Dual.mkv"
        },
        {
            "name": "Sultan Abdul Hamid",
            "year": null,
            "quality": "720p",
            "link": "https://atryh78.b-cdn.net/s3/upload/videos/2026/03/[Fibwatch.Com]Sultan.Abdul.Hamid.S01E106.Bengali.ORG.720p.mkv"
        },
        {
            "name": "Virgin River",
            "year": null,
            "quality": "720p",
            "link": "https://atryh78.b-cdn.net/s3/upload/videos/2026/03/[Fibwatch.Com]Virgin.River.S01.720p.Dual.mkv"
        },
        {
            "name": "Virgin River",
            "year": null,
            "quality": "480p",
            "link": "https://atryh78.b-cdn.net/s3/upload/videos/2026/03/[Fibwatch.Com]Virgin.River.S02.480p.Dual.mkv"
        },
        {
            "name": "Pennum Porattum  Dual",
            "year": "2026",
            "quality": "480P",
            "link": "https://atryh78.b-cdn.net/s3/upload/videos/2026/03/[Fibwatch.Com]Pennum.Porattum.(2026).Dual.480P.mkv"
        },
        {
            "name": "Chaya Brikkho",
            "year": null,
            "quality": "720P",
            "link": "https://atryh78.b-cdn.net/s3/upload/videos/2026/03/[Fibwatch.Com]Chaya.Brikkho.720P.mkv"
        },
        {
            "name": "Sultan Abdul Hamid",
            "year": null,
            "quality": "1080p",
            "link": "https://atryh78.b-cdn.net/s3/upload/videos/2026/03/[Fibwatch.Com]Sultan.Abdul.Hamid.S01E106.Bengali.ORG.1080p.mkv"
        },
        {
            "name": "Fast N Loud",
            "year": null,
            "quality": null,
            "link": "https://atryh78.b-cdn.net/s3/upload/videos/2026/03/[Fibwatch.Com]Fast.N.Loud.S01E11-15.Dual.mkv"
        },
        {
            "name": "Chaya Brikkho",
            "year": null,
            "quality": "480P",
            "link": "https://atryh78.b-cdn.net/s3/upload/videos/2026/03/[Fibwatch.Com]Chaya.Brikkho.480P.mkv"
        },
        {
            "name": "Chaya Brikkho",
            "year": null,
            "quality": "1080P",
            "link": "https://atryh78.b-cdn.net/s3/upload/videos/2026/03/[Fibwatch.Com]Chaya.Brikkho.1080P.mkv"
        },
        {
            "name": "Naagin",
            "year": null,
            "quality": "720P",
            "link": "https://atryh78.b-cdn.net/s3/upload/videos/2026/03/[Fibwatch.Com]Naagin.S07E21-22.Bengali.720P.mkv"
        },
        {
            "name": "Lawho Gouranger Naam Re  Bengali",
            "year": "2025",
            "quality": "720P",
            "link": "https://atryh78.b-cdn.net/s3/upload/videos/2026/03/[Fibwatch.Com]Lawho.Gouranger.Naam.Re.(2025).Bengali.720P.mkv"
        },
        {
            "name": "The 50",
            "year": null,
            "quality": "1080P",
            "link": "https://atryh78.b-cdn.net/s3/upload/videos/2026/03/[Fibwatch.Com]The.50.S01E39.1080P.mkv"
        },
        {
            "name": "Lawho Gouranger Naam Re  Bengali",
            "year": "2025",
            "quality": "480P",
            "link": "https://atryh78.b-cdn.net/s3/upload/videos/2026/03/[Fibwatch.Com]Lawho.Gouranger.Naam.Re.(2025).Bengali.480P.mkv"
        },
        {
            "name": "Lawho Gouranger Naam Re  Bengali",
            "year": "2025",
            "quality": "1080P",
            "link": "https://atryh78.b-cdn.net/s3/upload/videos/2026/03/[Fibwatch.Com]Lawho.Gouranger.Naam.Re.(2025).Bengali.1080P.mkv"
        },
        {
            "name": "Naagin",
            "year": null,
            "quality": "1080P",
            "link": "https://atryh78.b-cdn.net/s3/upload/videos/2026/03/[Fibwatch.Com]Naagin.S07E21-22.Bengali.1080P.mkv"
        },
        {
            "name": "Virgin River",
            "year": null,
            "quality": "720p",
            "link": "https://atryh78.b-cdn.net/s3/upload/videos/2026/03/[Fibwatch.Com]Virgin.River.S02.720p.Dual.mkv"
        },
        {
            "name": "Wheel Of Fortune",
            "year": "2026",
            "quality": "720P",
            "link": "https://atryh78.b-cdn.net/s3/upload/videos/2026/03/[Fibwatch.Com]Wheel.Of.Fortune.(2026).S01E30-31.Hindi.720P.mkv"
        },
        {
            "name": "Resort",
            "year": null,
            "quality": "720P",
            "link": "https://atryh78.b-cdn.net/s3/upload/videos/2026/03/[Fibwatch.Com]Resort.S01E01-04.720P.mkv"
        },
        {
            "name": "Pennum Porattum  Dual",
            "year": "2026",
            "quality": "1080P",
            "link": "https://atryh78.b-cdn.net/s3/upload/videos/2026/03/[Fibwatch.Com]Pennum.Porattum.(2026).Dual.1080P.mkv"
        },
        {
            "name": "The Taj Story 2025  Hindi",
            "year": null,
            "quality": "720p",
            "link": "https://atryh78.b-cdn.net/s3/upload/videos/2026/03/[Fibwatch.Com]The.Taj.Story.2025.720p.Hindi.mkv"
        },
        {
            "name": "The Taj Story 2025  Hindi",
            "year": null,
            "quality": "480p",
            "link": "https://atryh78.b-cdn.net/s3/upload/videos/2026/03/[Fibwatch.Com]The.Taj.Story.2025.480p.Hindi.mkv"
        },
        {
            "name": "The Taj Story 2025  Hindi",
            "year": null,
            "quality": "1080p",
            "link": "https://atryh78.b-cdn.net/s3/upload/videos/2026/03/[Fibwatch.Com]The.Taj.Story.2025.1080p.Hindi.mkv"
        },
        {
            "name": "Aspirants",
            "year": "2026",
            "quality": "720P",
            "link": "https://atryh78.b-cdn.net/s3/upload/videos/2026/03/[Fibwatch.Com]Aspirants.(2026).S03.720P.mkv"
        },
        {
            "name": "Aspirants",
            "year": "2026",
            "quality": "1080P",
            "link": "https://atryh78.b-cdn.net/s3/upload/videos/2026/03/[Fibwatch.Com]Aspirants.(2026).S03.1080P.mkv"
        },
        {
            "name": "LBW Love Beyond Wicket",
            "year": "2026",
            "quality": "720P",
            "link": "https://atryh78.b-cdn.net/s3/upload/videos/2026/03/[Fibwatch.Com]LBW.Love.Beyond.Wicket.(2026).S01E37-40.Dual.720P.mkv"
        },
        {
            "name": "The 50",
            "year": null,
            "quality": "720P",
            "link": "https://atryh78.b-cdn.net/s3/upload/videos/2026/03/[Fibwatch.Com]The.50.S01E38.720P.mkv"
        },
        {
            "name": "Funky  Dual",
            "year": "2026",
            "quality": "720P",
            "link": "https://atryh78.b-cdn.net/s3/upload/videos/2026/03/[Fibwatch.Com]Funky.(2026).Dual.720P.mkv"
        },
        {
            "name": "Pennum Porattum  Dual",
            "year": "2026",
            "quality": "720P",
            "link": "https://atryh78.b-cdn.net/s3/upload/videos/2026/03/[Fibwatch.Com]Pennum.Porattum.(2026).Dual.720P.mkv"
        },
        {
            "name": "Turbulence 2025  Dual",
            "year": null,
            "quality": "1080p",
            "link": "https://atryh78.b-cdn.net/s3/upload/videos/2026/03/[Fibwatch.Com]Turbulence.2025.1080p.Dual.mkv"
        },
        {
            "name": "LBW Love Beyond Wicket",
            "year": "2026",
            "quality": "1080P",
            "link": "https://atryh78.b-cdn.net/s3/upload/videos/2026/03/[Fibwatch.Com]LBW.Love.Beyond.Wicket.(2026).S01E37-40.Dual.1080P.mkv"
        },
        {
            "name": "Aspirants",
            "year": "2026",
            "quality": "480P",
            "link": "https://atryh78.b-cdn.net/s3/upload/videos/2026/03/[Fibwatch.Com]Aspirants.(2026).S03.480P.mkv"
        },
        {
            "name": "Resort",
            "year": null,
            "quality": "1080P",
            "link": "https://atryh78.b-cdn.net/s3/upload/videos/2026/03/[Fibwatch.Com]Resort.S01E01-04.1080P.mkv"
        },
        {
            "name": "The 50",
            "year": null,
            "quality": "1080P",
            "link": "https://atryh78.b-cdn.net/s3/upload/videos/2026/03/[Fibwatch.Com]The.50.S01E38.1080P.mkv"
        },
        {
            "name": "Madam Sengupta 2025  Hindi",
            "year": null,
            "quality": "1080p",
            "link": "https://atryh78.b-cdn.net/s3/upload/videos/2026/03/[Fibwatch.Com]Madam.Sengupta.2025.1080p.Hindi.mkv"
        }
    ]
}